rapidexec/__init__.py
rapidexec/cli.py
rapidexec/main.py
rapidexec/commands/__init__.py
rapidexec/commands/base.py
rapidexec/commands/command.py
rapidexec/commands/filters.py
rapidexec/config/__init__.py
rapidexec/console/__init__.py
rapidexec/console/progress_manager.py
rapidexec/console/singleton.py
rapidexec/console/test_2.py
rapidexec/console/wrapper.py
rapidexec/services/__init__.py
rapidexec/services/export.py
rapidexec/services/live.py
rapidexec/services/compose/__init__.py
rapidexec/services/compose/logs.py
rapidexec/services/docker/__init__.py
rapidexec/services/docker/logs.py
rapidexec/services/docker/ps.py
rapidexec-0.0.4.dist-info/METADATA
rapidexec-0.0.4.dist-info/WHEEL
rapidexec-0.0.4.dist-info/entry_points.txt
rapidexec-0.0.4.dist-info/licenses/LICENSE
rapidexec-0.0.4.dist-info/RECORD
