Metadata-Version: 2.1
Name: rapidexec
Version: 0.0.4
Summary: A simple, fast, and flexible way to execute commands in a Docker container.
Project-URL: Homepage, https://github.com/godd0t/rapidexec
License: MIT
License-File: LICENSE
Classifier: Development Status :: 1 - Planning
Classifier: Environment :: Web Environment
Classifier: Framework :: Django :: 4.2
Classifier: Intended Audience :: Developers
Classifier: License :: OSI Approved :: MIT License
Classifier: Operating System :: OS Independent
Classifier: Programming Language :: Python :: 3.11
Classifier: Topic :: Software Development :: Libraries :: Python Modules
Classifier: Topic :: Software Development :: Version Control :: Git
Classifier: Topic :: Utilities
Requires-Dist: click==8.1.3
Requires-Dist: rich==13.4.1
Provides-Extra: dev
Requires-Dist: black==23.3.0; extra == 'dev'
Requires-Dist: build==0.10.0; extra == 'dev'
Requires-Dist: coverage==7.2.7; extra == 'dev'
Requires-Dist: pytest-asyncio==0.21.0; extra == 'dev'
Requires-Dist: pytest-sugar==0.9.7; extra == 'dev'
Requires-Dist: pytest==7.3.1; extra == 'dev'
Requires-Dist: ruff==0.0.270; extra == 'dev'
Requires-Dist: twine==4.0.2; extra == 'dev'
Provides-Extra: docker
Requires-Dist: docker==6.1.2; extra == 'docker'
Provides-Extra: export
Requires-Dist: toml==0.10.2; extra == 'export'
